manga_notifier/__init__.py
manga_notifier/__version__.py
manga_notifier/cli.py
manga_notifier/download.py
manga_notifier/environments.py
manga_notifier/mangastream.py
manga_notifier/meow.py
manga_notifier/storage.py
manga_notifier-1.1.1.dist-info/DESCRIPTION.rst
manga_notifier-1.1.1.dist-info/METADATA
manga_notifier-1.1.1.dist-info/RECORD
manga_notifier-1.1.1.dist-info/WHEEL
manga_notifier-1.1.1.dist-info/entry_points.txt
manga_notifier-1.1.1.dist-info/metadata.json
manga_notifier-1.1.1.dist-info/top_level.txt
