Metadata-Version: 2.0
Name: manga-notifier
Version: 1.1.1
Summary: A command-line tool to keep updated of the new chapters manga.
Home-page: https://github.com/Germione/manga-notifier
Author: Jerome Pradier
Author-email: jerome.pradier@gmail.com
License: MIT
Keywords: tools manga entertainement
Platform: UNKNOWN
Classifier: Development Status :: 5 - Production/Stable
Classifier: Intended Audience :: Developers
Classifier: License :: OSI Approved :: MIT License
Classifier: Programming Language :: Python :: 2
Classifier: Programming Language :: Python :: 2.7
Classifier: Programming Language :: Python :: 3
Classifier: Programming Language :: Python :: 3.5
Classifier: Programming Language :: Python :: 3.6
Requires-Dist: requests
Requires-Dist: lxml
Requires-Dist: cssselect
Requires-Dist: click
